netin/__init__.py
netin/base_class.py
netin/algorithms/janus/__init__.py
netin/algorithms/janus/hypothesis.py
netin/algorithms/janus/janus.py
netin/algorithms/janus/janus_model_fitting.py
netin/algorithms/janus/janusgraph.py
netin/filters/__init__.py
netin/filters/active_nodes.py
netin/filters/filter.py
netin/filters/no_double_links.py
netin/filters/no_self_links.py
netin/filters/tests/__init__.py
netin/filters/tests/test_filters.py
netin/graphs/__init__.py
netin/graphs/binary_class_node_vector.py
netin/graphs/categorical_node_vector.py
netin/graphs/directed.py
netin/graphs/graph.py
netin/graphs/node_vector.py
netin/graphs/tests/__init__.py
netin/graphs/tests/test_binary_class_vector.py
netin/graphs/tests/test_categorical_node_vector.py
netin/graphs/tests/test_graph.py
netin/graphs/tests/test_node_vector.py
netin/link_formation_mechanisms/__init__.py
netin/link_formation_mechanisms/homophily.py
netin/link_formation_mechanisms/indegree_preferential_attachment.py
netin/link_formation_mechanisms/link_formation_mechanism.py
netin/link_formation_mechanisms/preferential_attachment.py
netin/link_formation_mechanisms/triadic_closure.py
netin/link_formation_mechanisms/two_class_homophily.py
netin/link_formation_mechanisms/uniform.py
netin/link_formation_mechanisms/tests/__init__.py
netin/link_formation_mechanisms/tests/test_homophily.py
netin/link_formation_mechanisms/tests/test_indegree_preferential_attachment.py
netin/link_formation_mechanisms/tests/test_preferential_attachment.py
netin/link_formation_mechanisms/tests/test_triadic_closure.py
netin/models/__init__.py
netin/models/barabasi_albert_model.py
netin/models/binary_class_model.py
netin/models/dh_model.py
netin/models/directed_model.py
netin/models/dpa_model.py
netin/models/dpah_model.py
netin/models/homophily_model.py
netin/models/model.py
netin/models/pa_model.py
netin/models/pah_model.py
netin/models/patch_model.py
netin/models/undirected_model.py
netin/models/tests/__init__.py
netin/models/tests/test_dh.py
netin-2.0.0a2.dist-info/LICENSE
netin-2.0.0a2.dist-info/METADATA
netin-2.0.0a2.dist-info/WHEEL
netin-2.0.0a2.dist-info/top_level.txt
netin-2.0.0a2.dist-info/RECORD
