Metadata-Version: 2.1
Name: netin
Version: 2.0.0a2
Summary: Python package to study inequalities in social networks
Home-page: https://github.com/CSHVienna/NetworkInequalities
Author: Lisette Espín-Noboa
Author-email: espin@csh.ac.at
Maintainer: NetIn Developers
Maintainer-email: netin-dev@googlegroups.com
Keywords: Networks,Inequalities,Social Networks,Ranking,InferenceGraph Theory,Mathematics,network,undirected,discrete mathematics,math
Platform: Linux
Platform: Mac OSX
Platform: Windows
Platform: Unix
Classifier: Development Status :: 3 - Alpha
Classifier: Intended Audience :: Developers
Classifier: Intended Audience :: Education
Classifier: Intended Audience :: Information Technology
Classifier: Intended Audience :: Science/Research
Classifier: Operating System :: OS Independent
Classifier: Programming Language :: Python :: 3.9
Classifier: Topic :: Software Development :: Libraries :: Python Modules
Classifier: Topic :: Scientific/Engineering
Classifier: Topic :: Scientific/Engineering :: Information Analysis
Classifier: Topic :: Scientific/Engineering :: Mathematics
Classifier: Topic :: Scientific/Engineering :: Physics
Requires-Python: >=3.9
License-File: LICENSE
Requires-Dist: networkx~=3.1
Requires-Dist: numpy~=1.24.2
Requires-Dist: setuptools~=67.6.1
Requires-Dist: matplotlib~=3.7.1
Requires-Dist: powerlaw~=1.5
Requires-Dist: pandas~=2.0.0
Requires-Dist: seaborn~=0.12.2
Requires-Dist: pqdm~=0.2.0
Requires-Dist: joblib~=1.2.0
Requires-Dist: scikit-learn~=1.2.2
Requires-Dist: pytest~=7.2.2
Requires-Dist: sympy~=1.11.1
Provides-Extra: default
Requires-Dist: networkx~=3.1; extra == "default"
Requires-Dist: numpy~=1.24.2; extra == "default"
Requires-Dist: setuptools~=67.6.1; extra == "default"
Requires-Dist: matplotlib~=3.7.1; extra == "default"
Requires-Dist: powerlaw~=1.5; extra == "default"
Requires-Dist: pandas~=2.0.0; extra == "default"
Requires-Dist: seaborn~=0.12.2; extra == "default"
Requires-Dist: pqdm~=0.2.0; extra == "default"
Requires-Dist: joblib~=1.2.0; extra == "default"
Requires-Dist: scikit-learn~=1.2.2; extra == "default"
Requires-Dist: pytest~=7.2.2; extra == "default"
Requires-Dist: sympy~=1.11.1; extra == "default"
Provides-Extra: test
Requires-Dist: setuptools~=67.6.1; extra == "test"
Requires-Dist: pytest~=7.2.2; extra == "test"
